rldog/agents/actor_critics/A2C.py
rldog/agents/base_agent.py
rldog/agents/DQN_based/DQN.py
rldog/agents/policy_gradients/PPO.py
rldog/agents/policy_gradients/reinforce.py
rldog/configs/base_config.py
rldog/configs/CartPole_config.py
rldog/configs/FrozenLake_config.py
rldog/constants.py
rldog/dataclasses/actor_critic_dataclasses.py
rldog/dataclasses/DQN_dataclasses.py
rldog/dataclasses/generic.py
rldog/dataclasses/policy_dataclasses.py
rldog/examples/CartPole.py
rldog/examples/FrozenLake.py
rldog/examples/FrozenLake_2.py
rldog/examples/FrozenLake_3.py
rldog/examples/FrozenLake_PPO.py
rldog/networks/networks.py
rldog/tools/logger.py
rldog/tools/plotters.py
rldog/tools/ppo_experience_generator.py
rldog-0.1.0.dist-info/LICENSE
rldog-0.1.0.dist-info/METADATA
rldog-0.1.0.dist-info/WHEEL
rldog-0.1.0.dist-info/RECORD
