Metadata-Version: 2.1
Name: rldog
Version: 0.1.0
Summary: Core 4 Reinforcement learning algorithms, implemented with very high quality code (think type hints, tests, pep8 etc). Very easy to use with gym or gym-like environments
License: MIT
Author: Charlie
Author-email: CharlieJackCoding@Gmail.com
Requires-Python: >=3.10,<4.0
Classifier: License :: OSI Approved :: MIT License
Classifier: Programming Language :: Python :: 3
Classifier: Programming Language :: Python :: 3.10
Classifier: Programming Language :: Python :: 3.11
Requires-Dist: gym (==0.26.2)
Requires-Dist: matplotlib (>=3.6.2,<4.0.0)
Requires-Dist: numpy (==1.23.5)
Requires-Dist: pytest (>=7.2.0,<8.0.0)
Requires-Dist: rich (>=13.0.0,<14.0.0)
Requires-Dist: torch (==1.13.1)
